exportpy/__init__.py
exportpy/_core.py
exportpy-0.0.1.dist-info/LICENSE
exportpy-0.0.1.dist-info/WHEEL
exportpy-0.0.1.dist-info/METADATA
exportpy-0.0.1.dist-info/RECORD
